{
    "BIN_FCSKU_DATA": {
        "B016DDRA2S": {
            "asin": "B016DDRA2S",
            "height": {
                "unit": "IN",
                "value": 1.99999999796
            },
            "length": {
                "unit": "IN",
                "value": 4.099999995818
            },
            "name": "YI 88002 16 MP Action Camera with Sony Sensor, 1080p 60 HD Video, 155\u00b0 Wide Angle Lens, Lime Green (Official U.S. Edition)",
            "normalizedName": "YI 88002 16 MP Action Camera with Sony Sensor, 1080p 60 HD Video, 155\u00b0 Wide Angle Lens, Lime Green (Official U.S. Edition)",
            "quantity": 3,
            "weight": {
                "unit": "pounds",
                "value": 0.4499999996226342
            },
            "width": {
                "unit": "IN",
                "value": 3.99999999592
            }
        }
    },
    "EXPECTED_QUANTITY": 3
}