{
    "BIN_FCSKU_DATA": {
        "B000K6U2MU": {
            "asin": "B000K6U2MU",
            "height": {
                "unit": "IN",
                "value": 1.2
            },
            "length": {
                "unit": "IN",
                "value": 3.6
            },
            "name": "Mattel Hot Wheels 1999 First Editions 1:64 Scale Red Semi-Fast Die Cast Car #008",
            "normalizedName": "Mattel Hot Wheels 1999 First Editions 1:64 Scale Red Semi-Fast Die Cast Car #008",
            "quantity": 1,
            "weight": null,
            "width": {
                "unit": "IN",
                "value": 1.5
            }
        },
        "B005JERLSG": {
            "asin": "B005JERLSG",
            "height": {
                "unit": "IN",
                "value": 0.599999999388
            },
            "length": {
                "unit": "IN",
                "value": 4.599999995308
            },
            "name": "Weaver Flat Leather Curb Straps - Color:Honey Leather:Bridle",
            "normalizedName": "Weaver Flat Leather Curb Straps - Color:Honey Leather:Bridle",
            "quantity": 1,
            "weight": {
                "unit": "pounds",
                "value": 0.022046001167587297
            },
            "width": {
                "unit": "IN",
                "value": 2.7999999971439995
            }
        },
        "B00TFAORBY": {
            "asin": "B00TFAORBY",
            "height": {
                "unit": "IN",
                "value": 3.199999996736
            },
            "length": {
                "unit": "IN",
                "value": 5.99999999388
            },
            "name": "Matchbox Ccw10 Pop-Up Rigs Assorted Styles",
            "normalizedName": "Matchbox Ccw10 Pop-Up Rigs Assorted Styles",
            "quantity": 1,
            "weight": {
                "unit": "pounds",
                "value": 0.6999999999999998
            },
            "width": {
                "unit": "IN",
                "value": 4.9999999949
            }
        },
        "B00ZQ3DWDS": {
            "asin": "B00ZQ3DWDS",
            "height": {
                "unit": "IN",
                "value": 1.199999998776
            },
            "length": {
                "unit": "IN",
                "value": 6.099999993778
            },
            "name": "X2 Innovations Pocket Digital Pedometer For Walking, Easy Step Counting & Activity Tracking! Get Fit & Healthy Fast With This Wireless Personal Tracker. Love It Or Your Money Back!",
            "normalizedName": "X2 Innovations Pocket Digital Pedometer For Walking, Easy Step Counting & Activity Tracking! Get Fit & Healthy Fast With This Wireless Personal Tracker. Love It Or Your Money Back!",
            "quantity": 1,
            "weight": {
                "unit": "pounds",
                "value": 0.16999999985743963
            },
            "width": {
                "unit": "IN",
                "value": 3.99999999592
            }
        }
    },
    "EXPECTED_QUANTITY": 4
}