{
    "BIN_FCSKU_DATA": {
        "B0063208Y2": {
            "asin": "B0063208Y2",
            "height": {
                "unit": "IN",
                "value": 0.599999999388
            },
            "length": {
                "unit": "IN",
                "value": 5.49999999439
            },
            "name": "The Strength Stability Bracelet (Blue Glow Small)",
            "normalizedName": "The Strength Stability Bracelet (Blue Glow Small)",
            "quantity": 8,
            "weight": {
                "unit": "pounds",
                "value": 0.05
            },
            "width": {
                "unit": "IN",
                "value": 4.49999999541
            }
        },
        "B00RGFX22A": {
            "asin": "B00RGFX22A",
            "height": {
                "unit": "IN",
                "value": 0.299999999694
            },
            "length": {
                "unit": "IN",
                "value": 10.399999989392
            },
            "name": "Simple Stories 138 Piece Epic Snap Double-Sided Cards & Bits/Pieces Die-Cuts Pack",
            "normalizedName": "Simple Stories 138 Piece Epic Snap Double-Sided Cards & Bits/Pieces Die-Cuts Pack",
            "quantity": 1,
            "weight": {
                "unit": "pounds",
                "value": 0.3499999997064932
            },
            "width": {
                "unit": "IN",
                "value": 6.99999999286
            }
        },
        "B010LRN6UC": {
            "asin": "B010LRN6UC",
            "height": {
                "unit": "IN",
                "value": 0.6999999992859999
            },
            "length": {
                "unit": "IN",
                "value": 6.99999999286
            },
            "name": "LG G4 Screen Protector, Scudo [LCD-Hard Coating] Screen Protector Film for LG G4 [Ultra High Definition] with Hard Coating/Anti Reflection/Anti Glare/Anti Bubble, Japanese Raw Material Manufactured in Korea",
            "normalizedName": "LG G4 Screen Protector, Scudo [LCD-Hard Coating] Screen Protector Film for LG G4 [Ultra High Definition] with Hard Coating/Anti Reflection/Anti Glare/Anti Bubble, Japanese Raw Material Manufactured in Korea",
            "quantity": 1,
            "weight": {
                "unit": "pounds",
                "value": 0.20000000000000004
            },
            "width": {
                "unit": "IN",
                "value": 3.899999996022
            }
        }
    },
    "EXPECTED_QUANTITY": 10
}