{
    "BIN_FCSKU_DATA": {
        "B003XL7WZO": {
            "asin": "B003XL7WZO",
            "height": {
                "unit": "IN",
                "value": 2.399999997552
            },
            "length": {
                "unit": "IN",
                "value": 8.399999991432
            },
            "name": "Aspects HummZinger HighView 12 oz Hanging Hummingbird Feeder",
            "normalizedName": "Aspects HummZinger HighView 12 oz Hanging Hummingbird Feeder",
            "quantity": 2,
            "weight": {
                "unit": "pounds",
                "value": 0.8000000000000002
            },
            "width": {
                "unit": "IN",
                "value": 7.899999991942001
            }
        }
    },
    "EXPECTED_QUANTITY": 2
}