{
    "BIN_FCSKU_DATA": {
        "0373777809": {
            "asin": "0373777809",
            "height": {
                "unit": "IN",
                "value": 1.0999999988780003
            },
            "length": {
                "unit": "IN",
                "value": 6.599999993268
            },
            "name": "Forsaken (Beartooth, Montana, Book 3)  (Hqn)",
            "normalizedName": "Forsaken (Beartooth, Montana, Book 3)  (Hqn)",
            "quantity": 1,
            "weight": {
                "unit": "pounds",
                "value": 0.4000000000000001
            },
            "width": {
                "unit": "IN",
                "value": 4.099999995818
            }
        },
        "1613734999": {
            "asin": "1613734999",
            "height": {
                "unit": "IN",
                "value": 0.799999999184
            },
            "length": {
                "unit": "IN",
                "value": 8.49999999133
            },
            "name": "Grandma Gatewood's Walk: The Inspiring Story of the Woman Who Saved the Appalachian Trail",
            "normalizedName": "Grandma Gatewood's Walk: The Inspiring Story of the Woman Who Saved the Appalachian Trail",
            "quantity": 1,
            "weight": {
                "unit": "pounds",
                "value": 0.6999999994129864
            },
            "width": {
                "unit": "IN",
                "value": 6.299999993574
            }
        },
        "B0099V6EKQ": {
            "asin": "B0099V6EKQ",
            "height": {
                "unit": "IN",
                "value": 4.399999995512001
            },
            "length": {
                "unit": "IN",
                "value": 6.299999993574
            },
            "name": "4.5 Inch Medieval Dragon Statue Figurine Desk Top Utility Holder",
            "normalizedName": "4.5 Inch Medieval Dragon Statue Figurine Desk Top Utility Holder",
            "quantity": 2,
            "weight": {
                "unit": "pounds",
                "value": 1.05
            },
            "width": {
                "unit": "IN",
                "value": 5.199999994696
            }
        },
        "B00L86CPT4": {
            "asin": "B00L86CPT4",
            "height": {
                "unit": "IN",
                "value": 0.899999999082
            },
            "length": {
                "unit": "IN",
                "value": 11.49999998827
            },
            "name": "HammerMill Proposal & Presentations Matte Bond 1 Sided",
            "normalizedName": "HammerMill Proposal & Presentations Matte Bond 1 Sided",
            "quantity": 1,
            "weight": {
                "unit": "pounds",
                "value": 1.2499999999999998
            },
            "width": {
                "unit": "IN",
                "value": 8.899999990922
            }
        }
    },
    "EXPECTED_QUANTITY": 5
}