{
    "BIN_FCSKU_DATA": {
        "B00D6FM0NG": {
            "asin": "B00D6FM0NG",
            "height": {
                "unit": "IN",
                "value": 0.299999999694
            },
            "length": {
                "unit": "IN",
                "value": 8.399999991432
            },
            "name": "NCAA Tennessee Volunteers Stationary Magnetic Polka Dot Design Note Pad",
            "normalizedName": "NCAA Tennessee Volunteers Stationary Magnetic Polka Dot Design Note Pad",
            "quantity": 1,
            "weight": {
                "unit": "pounds",
                "value": 0.25
            },
            "width": {
                "unit": "IN",
                "value": 3.899999996022
            }
        }
    },
    "EXPECTED_QUANTITY": 1
}