{
    "BIN_FCSKU_DATA": {
        "B002MQAWOY": {
            "asin": "B002MQAWOY",
            "height": {
                "unit": "IN",
                "value": 0.399999999592
            },
            "length": {
                "unit": "IN",
                "value": 4.099999995818
            },
            "name": "Vega Snowmobile Balaclava  (Black)",
            "normalizedName": "Vega Snowmobile Balaclava  (Black)",
            "quantity": 9,
            "weight": {
                "unit": "pounds",
                "value": 0.022046001186074866
            },
            "width": {
                "unit": "IN",
                "value": 3.899999996022
            }
        },
        "B0040CTTH4": {
            "asin": "B0040CTTH4",
            "height": {
                "unit": "IN",
                "value": 0.099999999898
            },
            "length": {
                "unit": "IN",
                "value": 6.99999999286
            },
            "name": "25 Toyota Trim Panel Retainer Clips 90467-10188 Sienna",
            "normalizedName": "25 Toyota Trim Panel Retainer Clips 90467-10188 Sienna",
            "quantity": 1,
            "weight": {
                "unit": "pounds",
                "value": 0.05000000000000001
            },
            "width": {
                "unit": "IN",
                "value": 3.099999996838
            }
        },
        "B00IAVHYSC": {
            "asin": "B00IAVHYSC",
            "height": {
                "unit": "IN",
                "value": 1.199999998776
            },
            "length": {
                "unit": "IN",
                "value": 2.49999999745
            },
            "name": "The Hillman Group The Hillman Group 4257 Cotterless Hitch Pin 3/8 x 2-1/8 In. (4-Pack)",
            "normalizedName": "(4-Pack) The Hillman Group The Hillman Group 4257 Cotterless Hitch Pin 3/8 x 2-1/8 In.",
            "quantity": 1,
            "weight": {
                "unit": "pounds",
                "value": 0.3499999999999999
            },
            "width": {
                "unit": "IN",
                "value": 2.099999997858
            }
        },
        "B00VHHIUNY": {
            "asin": "B00VHHIUNY",
            "height": {
                "unit": "IN",
                "value": 1.899999998062
            },
            "length": {
                "unit": "IN",
                "value": 4.9999999949
            },
            "name": "Quick Charge 2.0 AUKEY 3-Port USB Wall Charger",
            "normalizedName": "Quick Charge 2.0 AUKEY 3-Port USB Wall Charger",
            "quantity": 2,
            "weight": {
                "unit": "pounds",
                "value": 0.55
            },
            "width": {
                "unit": "IN",
                "value": 3.799999996124
            }
        },
        "B01BZVMZ2I": {
            "asin": "B01BZVMZ2I",
            "height": {
                "unit": "IN",
                "value": 1.199999998776
            },
            "length": {
                "unit": "IN",
                "value": 7.099999992758
            },
            "name": "iHome | Executive: 2-in-1 Micro USB & Apple MFi Certified Lightning Cable - Gold - See More Colors",
            "normalizedName": "iHome | Executive: 2-in-1 Micro USB & Apple MFi Certified Lightning Cable - Gold - See More Colors",
            "quantity": 1,
            "weight": {
                "unit": "pounds",
                "value": 0.30999999974003695
            },
            "width": {
                "unit": "IN",
                "value": 4.399999995512001
            }
        }
    },
    "EXPECTED_QUANTITY": 14
}