{
    "BIN_FCSKU_DATA": {
        "B00A3QBX0M": {
            "asin": "B00A3QBX0M",
            "height": {
                "unit": "IN",
                "value": 0.099999999898
            },
            "length": {
                "unit": "IN",
                "value": 2.1999999977560005
            },
            "name": "Pilot Uni Kurutoga with Rubber Grip Mechanical Pencil 0.5mm, Black (M56561P.24)",
            "normalizedName": "Pilot Uni Kurutoga with Rubber Grip Mechanical Pencil 0.5mm, Black (M56561P.24)",
            "quantity": 15,
            "weight": {
                "unit": "pounds",
                "value": 0.022046001186074866
            },
            "width": {
                "unit": "IN",
                "value": 1.99999999796
            }
        },
        "B00ZVT6DXI": {
            "asin": "B00ZVT6DXI",
            "height": {
                "unit": "IN",
                "value": 3.099999996838
            },
            "length": {
                "unit": "IN",
                "value": 5.49999999439
            },
            "name": "Best Heavy Duty Pencil Sharpener for Teachers, Classrooms, Schools and Offices",
            "normalizedName": "Best Heavy Duty Pencil Sharpener for Teachers, Classrooms, Schools and Offices",
            "quantity": 1,
            "weight": {
                "unit": "pounds",
                "value": 1.2
            },
            "width": {
                "unit": "IN",
                "value": 5.099999994798
            }
        },
        "B01FV031YK": {
            "asin": "B01FV031YK",
            "height": {
                "unit": "IN",
                "value": 2.699999997246
            },
            "length": {
                "unit": "IN",
                "value": 5.299999994594
            },
            "name": "Health Concerns - Three Immortals - 270 Tablets",
            "normalizedName": "Health Concerns - Three Immortals - 270 Tablets",
            "quantity": 1,
            "weight": {
                "unit": "pounds",
                "value": 0.6999999999999998
            },
            "width": {
                "unit": "IN",
                "value": 2.99999999694
            }
        }
    },
    "EXPECTED_QUANTITY": 17
}