{
    "BIN_FCSKU_DATA": {
        "B01AXGQKZO": {
            "asin": "B01AXGQKZO",
            "height": {
                "unit": "IN",
                "value": 2.899999997042
            },
            "length": {
                "unit": "IN",
                "value": 6.49999999337
            },
            "name": "Kingway Updated Version Chips 5 Pack Ink Cartridges Replacement for HP 934 935 934XL 935XL Use with HP OfficeJet Pro 6830 6230 6835 6815 6812 Printers",
            "normalizedName": "5 Pack Kingway Updated Version Chips Ink Cartridges Replacement for HP 934 935 934XL 935XL Use with HP OfficeJet Pro 6830 6230 6835 6815 6812 Printers",
            "quantity": 1,
            "weight": {
                "unit": "pounds",
                "value": 0.7299999993878289
            },
            "width": {
                "unit": "IN",
                "value": 3.6999999962260004
            }
        }
    },
    "EXPECTED_QUANTITY": 1
}