{
    "BIN_FCSKU_DATA": {
        "B000CHML8A": {
            "asin": "B000CHML8A",
            "height": {
                "unit": "IN",
                "value": 4.199999995716
            },
            "length": {
                "unit": "IN",
                "value": 16.699999982966
            },
            "name": "Gates 22901 Lower Radiator Hose",
            "normalizedName": "Gates 22901 Lower Radiator Hose",
            "quantity": 1,
            "weight": {
                "unit": "pounds",
                "value": 0.8
            },
            "width": {
                "unit": "IN",
                "value": 10.699999989086
            }
        },
        "B001A3U5V0": {
            "asin": "B001A3U5V0",
            "height": {
                "unit": "IN",
                "value": 0.299999999694
            },
            "length": {
                "unit": "IN",
                "value": 10.99999998878
            },
            "name": "Avery Legal Dividers, Standard Collated Sets, Letter Size, Side Tabs and 451-475 Tab Set (01348)",
            "normalizedName": "Avery Legal Dividers, Standard Collated Sets, Letter Size, Side Tabs and 451-475 Tab Set (01348)",
            "quantity": 1,
            "weight": {
                "unit": "pounds",
                "value": 0.45
            },
            "width": {
                "unit": "IN",
                "value": 8.799999991024
            }
        },
        "B0033WSTYQ": {
            "asin": "B0033WSTYQ",
            "height": {
                "unit": "IN",
                "value": 2.599999997348
            },
            "length": {
                "unit": "IN",
                "value": 11.399999988372
            },
            "name": "Monster Cable MCC AV 55 Universal Remote Control (Discontinued by Manufacturer)",
            "normalizedName": "Monster Cable MCC AV 55 Universal Remote Control (Discontinued by Manufacturer)",
            "quantity": 1,
            "weight": {
                "unit": "pounds",
                "value": 1.1
            },
            "width": {
                "unit": "IN",
                "value": 7.099999992758
            }
        },
        "B00MHYRMFI": {
            "asin": "B00MHYRMFI",
            "height": {
                "unit": "IN",
                "value": 2.399999997552
            },
            "length": {
                "unit": "IN",
                "value": 14.599999985108
            },
            "name": "It's a Wig Remi Touch Synthetic Lace Front Wig RT7 (2T27/613)",
            "normalizedName": "It's a Wig Remi Touch Synthetic Lace Front Wig RT7 (2T27/613)",
            "quantity": 1,
            "weight": {
                "unit": "pounds",
                "value": 0.45
            },
            "width": {
                "unit": "IN",
                "value": 7.199999992656
            }
        },
        "B00NWSTEJK": {
            "asin": "B00NWSTEJK",
            "height": {
                "unit": "IN",
                "value": 2.899999997042
            },
            "length": {
                "unit": "IN",
                "value": 13.099999986638
            },
            "name": "Oldelf Outdoor Sports Essentials Kit Bundle (15 Items)",
            "normalizedName": "Oldelf Outdoor Sports Essentials Kit Bundle (15 Items)",
            "quantity": 2,
            "weight": {
                "unit": "pounds",
                "value": 2.3500000000000005
            },
            "width": {
                "unit": "IN",
                "value": 9.399999990412
            }
        }
    },
    "EXPECTED_QUANTITY": 6
}