{
    "BIN_FCSKU_DATA": {
        "0323187358": {
            "asin": "0323187358",
            "height": {
                "unit": "IN",
                "value": 2.5984251942
            },
            "length": {
                "unit": "IN",
                "value": 11.1811023508
            },
            "name": "Pathophysiology Online for Pathophysiology (Access Code and Textbook Package): The Biologic Basis for Disease in Adults and Children, 7e",
            "normalizedName": "Pathophysiology Online for Pathophysiology (Access Code and Textbook Package): The Biologic Basis for Disease in Adults and Children, 7e",
            "quantity": 1,
            "weight": {
                "unit": "pounds",
                "value": 8.686124467313496
            },
            "width": {
                "unit": "IN",
                "value": 8.8976377862
            }
        },
        "B00DFVZOCA": {
            "asin": "B00DFVZOCA",
            "height": {
                "unit": "IN",
                "value": 1.2598425184
            },
            "length": {
                "unit": "IN",
                "value": 6.8503936938
            },
            "name": "StarTech.com USB 3.0 External Flash Multi Media Memory Card Reader (FCREADMICRO3)",
            "normalizedName": "StarTech.com USB 3.0 External Flash Multi Media Memory Card Reader (FCREADMICRO3)",
            "quantity": 1,
            "weight": {
                "unit": "pounds",
                "value": 0.17636800948859893
            },
            "width": {
                "unit": "IN",
                "value": 5.511811018
            }
        },
        "B00SVE65EM": {
            "asin": "B00SVE65EM",
            "height": {
                "unit": "IN",
                "value": 3.543307083
            },
            "length": {
                "unit": "IN",
                "value": 15.2755905356
            },
            "name": "Bath Toy - Submarine Spray Station - Battery Operated Water Pump With Hand Shower And More",
            "normalizedName": "Bath Toy - Submarine Spray Station - Battery Operated Water Pump With Hand Shower And More",
            "quantity": 1,
            "weight": {
                "unit": "pounds",
                "value": 1.8518640996302886
            },
            "width": {
                "unit": "IN",
                "value": 11.023622036
            }
        },
        "B016F7SKOY": {
            "asin": "B016F7SKOY",
            "height": {
                "unit": "IN",
                "value": 3.49999999643
            },
            "length": {
                "unit": "IN",
                "value": 14.599999985108
            },
            "name": "The Waving Flag Electronic Desktop American Flag With 2 Patriotic songs",
            "normalizedName": "The Waving Flag Electronic Desktop American Flag With 2 Patriotic songs",
            "quantity": 1,
            "weight": {
                "unit": "pounds",
                "value": 1.1999999989936914
            },
            "width": {
                "unit": "IN",
                "value": 9.099999990718
            }
        }
    },
    "EXPECTED_QUANTITY": 4
}